dbqt/app.py
dbqt/connections.py
dbqt/examples/athena_config.yaml.example
dbqt/examples/duckdb_config.yaml.example
dbqt/examples/mssql.yaml.example
dbqt/examples/oracle_config.yaml.example
dbqt/examples/snowflake_config.yaml.example
dbqt/tools/__init__.py
dbqt/tools/colcompare.py
dbqt/tools/combine.py
dbqt/tools/dbstats.py
dbqt/tools/dynamic_query.py
dbqt/tools/keyfinder.py
dbqt/tools/nullcheck.py
dbqt/tools/parquetizer.py
dbqt/tools/utils.py
dbqt-0.1.15.dist-info/METADATA
dbqt-0.1.15.dist-info/WHEEL
dbqt-0.1.15.dist-info/entry_points.txt
dbqt-0.1.15.dist-info/licenses/LICENSE
dbqt-0.1.15.dist-info/RECORD
