Metadata-Version: 2.4
Name: dbqt
Version: 0.1.15
Summary: DataBase Quality Tool
Project-URL: Repository, https://github.com/namilinklabs/dbqt
Project-URL: Documentation, https://github.com/namilinklabs/dbqt
Author: NamiLink
License: MIT
License-File: LICENSE
Classifier: Development Status :: 3 - Alpha
Classifier: Intended Audience :: Developers
Classifier: License :: OSI Approved :: MIT License
Classifier: Operating System :: OS Independent
Classifier: Programming Language :: Python :: 3
Classifier: Programming Language :: Python :: 3.8
Classifier: Programming Language :: Python :: 3.9
Classifier: Programming Language :: Python :: 3.10
Classifier: Programming Language :: Python :: 3.11
Classifier: Topic :: Software Development :: Quality Assurance
Requires-Python: >=3.9
Requires-Dist: boto3>=1.28.30
Requires-Dist: duckdb>=1.4.0
Requires-Dist: jaydebeapi>=1.2.3
Requires-Dist: openpyxl>=3.1.2
Requires-Dist: polars>=1.25.2
Requires-Dist: pyarrow>=18.1.0
Requires-Dist: pyodbc>=5.2.0
Requires-Dist: pyyaml>=6.0.1
Requires-Dist: reladiff>=0.6.0
Requires-Dist: sqeleton[mysql,postgresql,snowflake]>=0.1.7
Requires-Dist: tqdm>=4.67.1
